task3/counter.sv
//Counter increments a count everytime positive edge of clk is seen, en must also be true
//counter resets if rst is true
module counter#(
    parameter WIDTH = 8
)(

 // interface signals
 input logic clk, //input into counter block: clock
 input logic rst, //input into counter block: reset
 input logic en, //input into counter block: counter enable
 output logic [WIDTH-1:0] count //count output
);

always_ff @ (posedge clk) //This is dependent on clk edge, so conditions only check every positive clk edge, so as we can control
//clk edge impulse by enabling flag and as flag is only enabled when clicked then we can do 1 clock pulses
//Thus count iterates only when clk cycle happens and that is when flag is enabled

    if (rst) count <= {WIDTH{1'b0}}; //so if rst is true (1) then count = 0
    else count<= count + {{WIDTH-1{1'b0}}, en};
    /*else begin
        if (en) count<= count + {{WIDTH-1{1'b0}}, en};
        else count<= count - {{WIDTH-1{1'b0}}, !en}; //count<= count; is if we want to just increment 
    end*/
    //count<= count + {{WIDTH-1{1'b0}}, en}; //count increments by 1 as long as en is also true

endmodule

task3/counter.vcd
$version Generated by VerilatedVcd $end
$date Wed Oct 26 12:50:13 2022 $end
$timescale 1ps $end

 $scope module TOP $end
  $var wire  1 # clk $end
  $var wire  8 & count [7:0] $end
  $var wire  1 % en $end
  $var wire  1 $ rst $end
  $scope module counter $end
   $var wire 32 ' WIDTH [31:0] $end
   $var wire  1 # clk $end
   $var wire  8 & count [7:0] $end
   $var wire  1 % en $end
   $var wire  1 $ rst $end
  $upscope $end
 $upscope $end
$enddefinitions $end


#620
1#
0$
1%
b00000000 &
b00000000000000000000000000001000 '
#621
0#
#714
1#
b00000001 &
#715
0#
#752
1#
b00000010 &
#753
0#
#782
1#
b00000011 &
#783
0#
#806
1#
b00000100 &
#807
0#
#828
1#
b00000101 &
#829
0#
#852
1#
b00000110 &
#853
0#
#874
1#
b00000111 &
#875
0#
#898
1#
b00001000 &
#899
0#
#920
1#
b00001001 &
#921
0#
#944
1#
b00001010 &
#945
0#
#962
1#
b00001011 &
#963
0#
#982
1#
b00001100 &
#983
0#
#1002
1#
b00001101 &
#1003
0#
#1026
1#
b00001110 &
#1027
0#
#1046
1#
b00001111 &
#1047
0#
#1070
1#
b00010000 &
#1071
0#
#1092
1#
b00010001 &
#1093
0#
#1114
1#
b00010010 &
#1115
0#
#1134
1#
b00010011 &
#1135
0#
#1154
1#
b00010100 &
#1155
0#
#1176
1#
b00010101 &
#1177
0#
#1200
1#
b00010110 &
#1201
0#
#1214
1#
b00010111 &
#1215
0#
#1236
1#
b00011000 &
#1237
0#
#1256
1#
b00011001 &
#1257
0#
#1278
1#
b00011010 &
#1279
0#
#1300
1#
b00011011 &
#1301
0#
#1326
1#
b00011100 &
#1327
0#
#1344
1#
b00011101 &
#1345
0#
#1368
1#
b00011110 &
#1369
0#
#1390
1#
b00011111 &
#1391
0#
#1410
1#
b00100000 &
#1411
0#
#1434
1#
b00100001 &
#1435
0#
#1452
1#
b00100010 &
#1453
0#
#1478
1#
b00100011 &
#1479
0#
#1500
1#
b00100100 &
#1501
0#
#1524
1#
b00100101 &
#1525
0#
#1546
1#
b00100110 &
#1547
0#
#1568
1#
b00100111 &
#1569
0#
#1610
1#
b00101000 &
#1611
0#
#1656
1#
b00101001 &
#1657
0#
#2212
1#
b00101010 &
#2213
0#
#2588
1#
b00101011 &
#2589
0#
#2610
1#
b00101100 &
#2611
0#
#2636
1#
b00101101 &
#2637
0#
#2662
1#
b00101110 &
#2663
0#
#2682
1#
b00101111 &
#2683
0#
#2704
1#
b00110000 &
#2705
0#
#2726
1#
b00110001 &
#2727
0#
#2750
1#
b00110010 &
#2751
0#
#2772
1#
b00110011 &
#2773
0#
#2794
1#
b00110100 &
#2795
0#
#2816
1#
b00110101 &
#2817
0#
#2838
1#
b00110110 &
#2839
0#
#2862
1#
b00110111 &
#2863
0#
#2882
1#
b00111000 &
#2883
0#
#2904
1#
b00111001 &
#2905
0#
#2926
1#
b00111010 &
#2927
0#
#2948
1#
b00111011 &
#2949
0#
#2962
1#
b00111100 &
#2963
0#
#2986
1#
b00111101 &
#2987
0#
#3006
1#
b00111110 &
#3007
0#
#3026
1#
b00111111 &
#3027
0#
#3044
1#
b01000000 &
#3045
0#
#3062
1#
b01000001 &
#3063
0#
#3082
1#
b01000010 &
#3083
0#
#3104
1#
b01000011 &
#3105
0#
#3136
1#
b01000100 &
#3137
0#
#3156
1#
b01000101 &
#3157
0#
#3176
1#
b01000110 &
#3177
0#
#3194
1#
b01000111 &
#3195
0#
#3212
1#
b01001000 &
#3213
0#
#3228
1#
b01001001 &
#3229
0#
#3246
1#
b01001010 &
#3247
0#
#3262
1#
b01001011 &
#3263
0#
#3282
1#
b01001100 &
#3283
0#
#3320
1#
b01001101 &
#3321
0#
#3344
1#
b01001110 &
#3345
0#
#3366
1#
b01001111 &
#3367
0#
#3386
1#
b01010000 &
#3387
0#
#3408
1#
b01010001 &
#3409
0#
#3430
1#
b01010010 &
#3431
0#
#3450
1#
b01010011 &
#3451
0#
#3470
1#
b01010100 &
#3471
0#
#3488
1#
b01010101 &
#3489
0#
#3520
1#
b01010110 &
#3521
0#
#3540
1#
b01010111 &
#3541
0#
#3562
1#
b01011000 &
#3563
0#
#3582
1#
b01011001 &
#3583
0#
#3598
1#
b01011010 &
#3599
0#
#3620
1#
b01011011 &
#3621
0#
#3910
1#
b01011100 &
