task2/.vscode/counter.sv
//Counter increments a count everytime positive edge of clk is seen, en must also be true
//counter resets if rst is true
module counter#(
    parameter WIDTH = 8
)(

 // interface signals
 input logic clk, //input into counter block: clock
 input logic rst, //input into counter block: reset
 input logic en, //input into counter block: counter enable
 output logic [WIDTH-1:0] count //count output
);

always_ff @ (posedge clk)
    if (rst) count <= {WIDTH{1'b0}}; //so if rst is true (1) then count = 0
    else count<= count + {{WIDTH-1{1'b0}}, en}; //count increments by 1 as long as en is also true

endmodule

task2/counter.vcd
$version Generated by VerilatedVcd $end
$date Wed Oct 26 12:38:40 2022 $end
$timescale 1ps $end

 $scope module TOP $end
  $var wire  1 # clk $end
  $var wire  8 & count [7:0] $end
  $var wire  1 % en $end
  $var wire  1 $ rst $end
  $scope module counter $end
   $var wire 32 ' WIDTH [31:0] $end
   $var wire  1 # clk $end
   $var wire  8 & count [7:0] $end
   $var wire  1 % en $end
   $var wire  1 $ rst $end
  $upscope $end
 $upscope $end
$enddefinitions $end


#0
1#
1$
0%
b00000000 &
b00000000000000000000000000001000 '
#1
0#
#2
1#
#3
0#
#4
1#
#5
0#
#6
1#
0$
#7
0#
#8
1#
b11111111 &
#9
0#
#10
1#
b11111110 &
#11
0#
#12
1#
b11111101 &
#13
0#
#14
1#
b11111100 &
#15
0#
#16
1#
b11111011 &
#17
0#
#18
1#
b11111010 &
#19
0#
#20
1#
b11111001 &
#21
0#
#22
1#
b11111000 &
#23
0#
#24
1#
b11110111 &
#25
0#
#26
1#
b11110110 &
#27
0#
#28
1#
b11110101 &
#29
0#
#30
1#
b11110100 &
#31
0#
#32
1#
1$
b11110011 &
#33
0#
#34
1#
0$
b00000000 &
#35
0#
#36
1#
b11111111 &
#37
0#
#38
1#
b11111110 &
#39
0#
#40
1#
b11111101 &
#41
0#
#42
1#
b11111100 &
#43
0#
#44
1#
b11111011 &
#45
0#
#46
1#
b11111010 &
#47
0#
#48
1#
b11111001 &
#49
0#
#50
1#
b11111000 &
#51
0#
#52
1#
b11110111 &
#53
0#
#54
1#
b11110110 &
#55
0#
#56
1#
b11110101 &
#57
0#
#58
1#
b11110100 &
#59
0#
#60
1#
b11110011 &
#61
0#
#62
1#
b11110010 &
#63
0#
#64
1#
b11110001 &
#65
0#
#66
1#
b11110000 &
#67
0#
#68
1#
b11101111 &
#69
0#
#70
1#
b11101110 &
#71
0#
#72
1#
b11101101 &
#73
0#
#74
1#
b11101100 &
#75
0#
#76
1#
b11101011 &
#77
0#
#78
1#
b11101010 &
#79
0#
#80
1#
b11101001 &
#81
0#
#82
1#
b11101000 &
#83
0#
#84
1#
b11100111 &
#85
0#
#86
1#
b11100110 &
#87
0#
#88
1#
b11100101 &
#89
0#
#90
1#
b11100100 &
#91
0#
#92
1#
b11100011 &
#93
0#
#94
1#
b11100010 &
#95
0#
#96
1#
b11100001 &
#97
0#
#98
1#
b11100000 &
#99
0#
#100
1#
b11011111 &
#101
0#
#102
1#
b11011110 &
#103
0#
#104
1#
b11011101 &
#105
0#
#106
1#
b11011100 &
#107
0#
#108
1#
b11011011 &
#109
0#
#110
1#
b11011010 &
#111
0#
#112
1#
b11011001 &
#113
0#
#114
1#
b11011000 &
#115
0#
#116
1#
b11010111 &
#117
0#
#118
1#
b11010110 &
#119
0#
#120
1#
b11010101 &
#121
0#
#122
1#
b11010100 &
#123
0#
#124
1#
b11010011 &
#125
0#
#126
1#
b11010010 &
#127
0#
#128
1#
b11010001 &
#129
0#
#130
1#
b11010000 &
#131
0#
#132
1#
b11001111 &
#133
0#
#134
1#
b11001110 &
#135
0#
#136
1#
b11001101 &
#137
0#
#138
1#
b11001100 &
#139
0#
#140
1#
b11001011 &
#141
0#
#142
1#
b11001010 &
#143
0#
#144
1#
b11001001 &
#145
0#
#146
1#
b11001000 &
#147
0#
#148
1#
b11000111 &
#149
0#
#150
1#
b11000110 &
#151
0#
#152
1#
b11000101 &
#153
0#
#154
1#
b11000100 &
#155
0#
#156
1#
b11000011 &
#157
0#
#158
1#
b11000010 &
#159
0#
#160
1#
b11000001 &
#161
0#
#162
1#
b11000000 &
#163
0#
#164
1#
b10111111 &
#165
0#
#166
1#
b10111110 &
#167
0#
#168
1#
b10111101 &
#169
0#
#170
1#
b10111100 &
#171
0#
#172
1#
b10111011 &
#173
0#
#174
1#
b10111010 &
#175
0#
#176
1#
b10111001 &
#177
0#
#178
1#
b10111000 &
#179
0#
#180
1#
b10110111 &
#181
0#
#182
1#
b10110110 &
#183
0#
#184
1#
b10110101 &
#185
0#
#186
1#
b10110100 &
#187
0#
#188
1#
b10110011 &
#189
0#
#190
1#
b10110010 &
#191
0#
#192
1#
b10110001 &
#193
0#
#194
1#
b10110000 &
#195
0#
#196
1#
b10101111 &
#197
0#
#198
1#
b10101110 &
#199
0#
#200
1#
b10101101 &
#201
0#
#202
1#
b10101100 &
#203
0#
#204
1#
b10101011 &
#205
0#
#206
1#
b10101010 &
#207
0#
#208
1#
b10101001 &
#209
0#
#210
1#
b10101000 &
#211
0#
#212
1#
b10100111 &
#213
0#
#214
1#
b10100110 &
#215
0#
#216
1#
b10100101 &
#217
0#
#218
1#
b10100100 &
#219
0#
#220
1#
1%
b10100011 &
#221
0#
#222
1#
b10100100 &
#223
0#
#224
1#
b10100101 &
#225
0#
#226
1#
b10100110 &
#227
0#
#228
1#
b10100111 &
#229
0#
#230
1#
b10101000 &
#231
0#
#232
1#
b10101001 &
#233
0#
#234
1#
b10101010 &
#235
0#
#236
1#
b10101011 &
#237
0#
#238
1#
b10101100 &
#239
0#
#240
1#
b10101101 &
#241
0#
#242
1#
b10101110 &
#243
0#
#244
1#
b10101111 &
#245
0#
#246
1#
b10110000 &
#247
0#
#248
1#
b10110001 &
#249
0#
#250
1#
b10110010 &
#251
0#
#252
1#
b10110011 &
#253
0#
#254
1#
b10110100 &
#255
0#
#256
1#
b10110101 &
#257
0#
#258
1#
b10110110 &
#259
0#
#260
1#
b10110111 &
#261
0#
#262
1#
b10111000 &
#263
0#
#264
1#
b10111001 &
#265
0#
#266
1#
b10111010 &
#267
0#
#268
1#
b10111011 &
#269
0#
#270
1#
b10111100 &
#271
0#
#272
1#
b10111101 &
#273
0#
#274
1#
b10111110 &
#275
0#
#276
1#
b10111111 &
#277
0#
#278
1#
b11000000 &
#279
0#
#280
1#
b11000001 &
#281
0#
#282
1#
b11000010 &
#283
0#
#284
1#
b11000011 &
#285
0#
#286
1#
b11000100 &
#287
0#
#288
1#
b11000101 &
#289
0#
#290
1#
b11000110 &
#291
0#
#292
1#
b11000111 &
#293
0#
#294
1#
b11001000 &
#295
0#
#296
1#
b11001001 &
#297
0#
#298
1#
b11001010 &
#299
0#
#300
1#
b11001011 &
#301
0#
#302
1#
b11001100 &
#303
0#
#304
1#
b11001101 &
#305
0#
#306
1#
b11001110 &
#307
0#
#308
1#
b11001111 &
#309
0#
#310
1#
b11010000 &
#311
0#
#312
1#
b11010001 &
#313
0#
#314
1#
b11010010 &
#315
0#
#316
1#
b11010011 &
#317
0#
#318
1#
b11010100 &
#319
0#
#320
1#
b11010101 &
#321
0#
#322
1#
b11010110 &
#323
0#
#324
1#
b11010111 &
#325
0#
#326
1#
b11011000 &
#327
0#
#328
1#
b11011001 &
#329
0#
#330
1#
b11011010 &
#331
0#
#332
1#
b11011011 &
#333
0#
#334
1#
b11011100 &
#335
0#
#336
1#
b11011101 &
#337
0#
#338
1#
b11011110 &
#339
0#
#340
1#
b11011111 &
#341
0#
#342
1#
b11100000 &
#343
0#
#344
1#
b11100001 &
#345
0#
#346
1#
b11100010 &
#347
0#
#348
1#
b11100011 &
#349
0#
#350
1#
b11100100 &
#351
0#
#352
1#
b11100101 &
#353
0#
#354
1#
b11100110 &
#355
0#
#356
1#
b11100111 &
#357
0#
#358
1#
b11101000 &
#359
0#
#360
1#
b11101001 &
#361
0#
#362
1#
b11101010 &
#363
0#
#364
1#
b11101011 &
#365
0#
#366
1#
b11101100 &
#367
0#
#368
1#
b11101101 &
#369
0#
#370
1#
b11101110 &
#371
0#
#372
1#
b11101111 &
#373
0#
#374
1#
b11110000 &
#375
0#
#376
1#
b11110001 &
#377
0#
#378
1#
b11110010 &
#379
0#
#380
1#
b11110011 &
#381
0#
#382
1#
b11110100 &
#383
0#
#384
1#
b11110101 &
#385
0#
#386
1#
b11110110 &
#387
0#
#388
1#
b11110111 &
#389
0#
#390
1#
b11111000 &
#391
0#
#392
1#
b11111001 &
#393
0#
#394
1#
b11111010 &
#395
0#
#396
1#
b11111011 &
#397
0#
#398
1#
b11111100 &
#399
0#
#400
1#
b11111101 &
#401
0#
#402
1#
b11111110 &
#403
0#
#404
1#
b11111111 &
#405
0#
#406
1#
b00000000 &
#407
0#
#408
1#
b00000001 &
#409
0#
#410
1#
b00000010 &
#411
0#
#412
1#
b00000011 &
#413
0#
#414
1#
b00000100 &
#415
0#
#416
1#
b00000101 &
#417
0#
#418
1#
b00000110 &
#419
0#
#420
1#
b00000111 &
#421
0#
#422
1#
b00001000 &
#423
0#
#424
1#
b00001001 &
#425
0#
#426
1#
b00001010 &
#427
0#
#428
1#
b00001011 &
#429
0#
#430
1#
b00001100 &
#431
0#
#432
1#
b00001101 &
#433
0#
#434
1#
b00001110 &
#435
0#
#436
1#
b00001111 &
#437
0#
#438
1#
b00010000 &
#439
0#
#440
1#
b00010001 &
#441
0#
#442
1#
b00010010 &
#443
0#
#444
1#
b00010011 &
#445
0#
#446
1#
b00010100 &
#447
0#
#448
1#
b00010101 &
#449
0#
#450
1#
b00010110 &
#451
0#
#452
1#
b00010111 &
#453
0#
#454
1#
b00011000 &
#455
0#
#456
1#
b00011001 &
#457
0#
#458
1#
b00011010 &
#459
0#
#460
1#
b00011011 &
#461
0#
#462
1#
b00011100 &
#463
0#
#464
1#
b00011101 &
#465
0#
#466
1#
b00011110 &
#467
0#
#468
1#
b00011111 &
#469
0#
#470
1#
b00100000 &
#471
0#
#472
1#
b00100001 &
#473
0#
#474
1#
b00100010 &
#475
0#
#476
1#
b00100011 &
#477
0#
#478
1#
b00100100 &
#479
0#
#480
1#
b00100101 &
#481
0#
#482
1#
b00100110 &
#483
0#
#484
1#
b00100111 &
#485
0#
#486
1#
b00101000 &
#487
0#
#488
1#
b00101001 &
#489
0#
#490
1#
b00101010 &
#491
0#
#492
1#
b00101011 &
#493
0#
#494
1#
b00101100 &
#495
0#
#496
1#
b00101101 &
#497
0#
#498
1#
b00101110 &
#499
0#
#500
1#
b00101111 &
#501
0#
#502
1#
b00110000 &
#503
0#
#504
1#
b00110001 &
#505
0#
#506
1#
b00110010 &
#507
0#
#508
1#
b00110011 &
#509
0#
#510
1#
b00110100 &
#511
0#
#512
1#
b00110101 &
#513
0#
#514
1#
b00110110 &
#515
0#
#516
1#
b00110111 &
#517
0#
#518
1#
b00111000 &
#519
0#
#520
1#
b00111001 &
#521
0#
#522
1#
b00111010 &
#523
0#
#524
1#
b00111011 &
#525
0#
#526
1#
b00111100 &
#527
0#
#528
1#
b00111101 &
#529
0#
#530
1#
b00111110 &
#531
0#
#532
1#
b00111111 &
#533
0#
#534
1#
b01000000 &
#535
0#
#536
1#
b01000001 &
#537
0#
#538
1#
b01000010 &
#539
0#
#540
1#
b01000011 &
#541
0#
#542
1#
b01000100 &
#543
0#
#544
1#
b01000101 &
#545
0#
#546
1#
b01000110 &
#547
0#
#548
1#
b01000111 &
#549
0#
#550
1#
b01001000 &
#551
0#
#552
1#
b01001001 &
#553
0#
#554
1#
b01001010 &
#555
0#
#556
1#
b01001011 &
#557
0#
#558
1#
b01001100 &
#559
0#
#560
1#
b01001101 &
#561
0#
#562
1#
b01001110 &
#563
0#
#564
1#
b01001111 &
#565
0#
#566
1#
b01010000 &
#567
0#
#568
1#
b01010001 &
#569
0#
#570
1#
b01010010 &
#571
0#
#572
1#
b01010011 &
#573
0#
#574
1#
b01010100 &
#575
0#
#576
1#
b01010101 &
#577
0#
#578
1#
b01010110 &
#579
0#
#580
1#
b01010111 &
#581
0#
#582
1#
b01011000 &
#583
0#
#584
1#
b01011001 &
#585
0#
#586
1#
b01011010 &
#587
0#
#588
1#
b01011011 &
#589
0#
#590
1#
b01011100 &
#591
0#
#592
1#
b01011101 &
#593
0#
#594
1#
b01011110 &
#595
0#
#596
1#
b01011111 &
#597
0#
#598
1#
b01100000 &
#599
0#
#600
1#
b01100001 &
#601
0#
#602
1#
b01100010 &
#603
0#
#604
1#
b01100011 &
#605
0#
#606
1#
b01100100 &
#607
0#
#608
1#
b01100101 &
#609
0#
#610
1#
b01100110 &
#611
0#
#612
1#
b01100111 &
#613
0#
#614
1#
b01101000 &
#615
0#
#616
1#
b01101001 &
#617
0#
#618
1#
b01101010 &
#619
0#
#620
1#
b01101011 &
#621
0#
#622
1#
b01101100 &
#623
0#
#624
1#
b01101101 &
#625
0#
#626
1#
b01101110 &
#627
0#
#628
1#
b01101111 &
#629
0#
#630
1#
b01110000 &
#631
0#
#632
1#
b01110001 &
#633
0#
#634
1#
b01110010 &
#635
0#
#636
1#
b01110011 &
#637
0#
#638
1#
b01110100 &
#639
0#
#640
1#
b01110101 &
#641
0#
#642
1#
b01110110 &
#643
0#
#644
1#
b01110111 &
#645
0#
#646
1#
b01111000 &
#647
0#
#648
1#
b01111001 &
#649
0#
#650
1#
b01111010 &
#651
0#
#652
1#
0%
b01111011 &
#653
0#
#654
1#
b01111010 &
#655
0#
#656
1#
b01111001 &
#657
0#
#658
1#
b01111000 &
#659
0#
#660
1#
b01110111 &
#661
0#
#662
1#
b01110110 &
#663
0#
#664
1#
b01110101 &
#665
0#
#666
1#
b01110100 &
#667
0#
#668
1#
b01110011 &
#669
0#
#670
1#
b01110010 &
#671
0#
#672
1#
b01110001 &
#673
0#
#674
1#
b01110000 &
#675
0#
#676
1#
b01101111 &
#677
0#
#678
1#
b01101110 &
#679
0#
#680
1#
b01101101 &
#681
0#
#682
1#
b01101100 &
#683
0#
#684
1#
b01101011 &
#685
0#
#686
1#
b01101010 &
#687
0#
#688
1#
b01101001 &
#689
0#
#690
1#
b01101000 &
#691
0#
#692
1#
b01100111 &
#693
0#
#694
1#
b01100110 &
#695
0#
#696
1#
b01100101 &
#697
0#
#698
1#
b01100100 &
#699
0#
#700
1#
b01100011 &
#701
0#
#702
1#
b01100010 &
#703
0#
#704
1#
b01100001 &
#705
0#
#706
1#
b01100000 &
#707
0#
#708
1#
b01011111 &
#709
0#
#710
1#
b01011110 &
#711
0#
#712
1#
b01011101 &
#713
0#
#714
1#
b01011100 &
#715
0#
#716
1#
b01011011 &
#717
0#
#718
1#
b01011010 &
#719
0#
#720
1#
b01011001 &
#721
0#
#722
1#
b01011000 &
#723
0#
#724
1#
b01010111 &
#725
0#
#726
1#
b01010110 &
#727
0#
#728
1#
b01010101 &
#729
0#
#730
1#
b01010100 &
#731
0#
#732
1#
b01010011 &
#733
0#
#734
1#
b01010010 &
#735
0#
#736
1#
b01010001 &
#737
0#
#738
1#
b01010000 &
#739
0#
#740
1#
b01001111 &
#741
0#
#742
1#
b01001110 &
#743
0#
#744
1#
b01001101 &
#745
0#
#746
1#
b01001100 &
#747
0#
#748
1#
b01001011 &
#749
0#
#750
1#
b01001010 &
#751
0#
#752
1#
b01001001 &
#753
0#
#754
1#
b01001000 &
#755
0#
#756
1#
b01000111 &
#757
0#
#758
1#
b01000110 &
#759
0#
#760
1#
b01000101 &
#761
0#
#762
1#
b01000100 &
#763
0#
#764
1#
b01000011 &
#765
0#
#766
1#
b01000010 &
#767
0#
#768
1#
b01000001 &
#769
0#
#770
1#
b01000000 &
#771
0#
#772
1#
b00111111 &
#773
0#
#774
1#
b00111110 &
#775
0#
#776
1#
b00111101 &
#777
0#
#778
1#
b00111100 &
#779
0#
#780
1#
b00111011 &
#781
0#
#782
1#
b00111010 &
#783
0#
#784
1#
b00111001 &
#785
0#
#786
1#
b00111000 &
#787
0#
#788
1#
b00110111 &
#789
0#
#790
1#
b00110110 &
#791
0#
#792
1#
b00110101 &
#793
0#
#794
1#
b00110100 &
#795
0#
#796
1#
b00110011 &
#797
0#
#798
1#
b00110010 &
#799
0#
#800
1#
b00110001 &
#801
0#
#802
1#
b00110000 &
#803
0#
#804
1#
b00101111 &
#805
0#
#806
1#
b00101110 &
#807
0#
#808
1#
b00101101 &
#809
0#
#810
1#
b00101100 &
#811
0#
#812
1#
b00101011 &
#813
0#
#814
1#
b00101010 &
#815
0#
#816
1#
b00101001 &
#817
0#
#818
1#
b00101000 &
#819
0#
#820
1#
b00100111 &
#821
0#
#822
1#
b00100110 &
#823
0#
#824
1#
b00100101 &
#825
0#
#826
1#
b00100100 &
#827
0#
#828
1#
b00100011 &
#829
0#
#830
1#
b00100010 &
#831
0#
#832
1#
b00100001 &
#833
0#
#834
1#
1%
b00100000 &
#835
0#
#836
1#
b00100001 &
#837
0#
#838
1#
b00100010 &
#839
0#
#840
1#
b00100011 &
#841
0#
#842
1#
b00100100 &
#843
0#
#844
1#
b00100101 &
#845
0#
#846
1#
b00100110 &
#847
0#
#848
1#
b00100111 &
#849
0#
#850
1#
b00101000 &
#851
0#
#852
1#
b00101001 &
#853
0#
#854
1#
b00101010 &
#855
0#
#856
1#
b00101011 &
#857
0#
#858
1#
b00101100 &
#859
0#
#860
1#
b00101101 &
#861
0#
#862
1#
b00101110 &
#863
0#
#864
1#
b00101111 &
#865
0#
#866
1#
b00110000 &
#867
0#
#868
1#
b00110001 &
#869
0#
#870
1#
b00110010 &
#871
0#
#872
1#
b00110011 &
#873
0#
#874
1#
b00110100 &
#875
0#
#876
1#
b00110101 &
#877
0#
#878
1#
b00110110 &
#879
0#
#880
1#
b00110111 &
#881
0#
#882
1#
b00111000 &
#883
0#
#884
1#
b00111001 &
#885
0#
#886
1#
b00111010 &
#887
0#
#888
1#
b00111011 &
#889
0#
#890
1#
b00111100 &
#891
0#
#892
1#
b00111101 &
#893
0#
#894
1#
b00111110 &
#895
0#
#896
1#
b00111111 &
#897
0#
#898
1#
b01000000 &
#899
0#
#900
1#
b01000001 &
#901
0#
#902
1#
b01000010 &
#903
0#
#904
1#
b01000011 &
#905
0#
#906
1#
b01000100 &
#907
0#
#908
1#
b01000101 &
#909
0#
#910
1#
b01000110 &
#911
0#
#912
1#
b01000111 &
#913
0#
#914
1#
b01001000 &
#915
0#
#916
1#
b01001001 &
#917
0#
#918
1#
b01001010 &
#919
0#
#920
1#
b01001011 &
#921
0#
#922
1#
b01001100 &
#923
0#
#924
1#
b01001101 &
#925
0#
#926
1#
b01001110 &
#927
0#
#928
1#
b01001111 &
#929
0#
#930
1#
b01010000 &
#931
0#
#932
1#
b01010001 &
#933
0#
#934
1#
b01010010 &
#935
0#
#936
1#
b01010011 &
#937
0#
#938
1#
b01010100 &
#939
0#
#940
1#
b01010101 &
#941
0#
#942
1#
b01010110 &
#943
0#
#944
1#
b01010111 &
#945
0#
#946
1#
b01011000 &
#947
0#
#948
1#
b01011001 &
#949
0#
#950
1#
b01011010 &
#951
0#
#952
1#
b01011011 &
#953
0#
#954
1#
b01011100 &
#955
0#
#956
1#
b01011101 &
#957
0#
#958
1#
b01011110 &
#959
0#
#960
1#
b01011111 &
#961
0#
#962
1#
b01100000 &
#963
0#
#964
1#
b01100001 &
#965
0#
#966
1#
b01100010 &
#967
0#
#968
1#
b01100011 &
#969
0#
#970
1#
b01100100 &
#971
0#
#972
1#
b01100101 &
#973
0#
#974
1#
b01100110 &
#975
0#
#976
1#
b01100111 &
#977
0#
#978
1#
b01101000 &
#979
0#
#980
1#
b01101001 &
#981
0#
#982
1#
b01101010 &
#983
0#
#984
1#
b01101011 &
#985
0#
#986
1#
b01101100 &
#987
0#
#988
1#
b01101101 &
#989
0#
#990
1#
b01101110 &
#991
0#
#992
1#
b01101111 &
#993
0#
#994
1#
b01110000 &
#995
0#
#996
1#
b01110001 &
#997
0#
#998
1#
b01110010 &
#999
0#
#1000
1#
b01110011 &
#1001
0#
#1002
1#
b01110100 &
#1003
0#
#1004
1#
b01110101 &
#1005
0#
#1006
1#
b01110110 &
#1007
0#
#1008
1#
b01110111 &
#1009
0#
#1010
1#
b01111000 &
#1011
0#
#1012
1#
b01111001 &
#1013
0#
#1014
1#
b01111010 &
#1015
0#
#1016
1#
b01111011 &
#1017
0#
#1018
1#
b01111100 &
#1019
0#
#1020
1#
b01111101 &
#1021
0#
#1022
1#
b01111110 &
#1023
0#
#1024
1#
b01111111 &
#1025
0#
#1026
1#
b10000000 &
#1027
0#
#1028
1#
b10000001 &
#1029
0#
#1030
1#
b10000010 &
#1031
0#
#1032
1#
b10000011 &
#1033
0#
#1034
1#
b10000100 &
#1035
0#
#1036
1#
b10000101 &
#1037
0#
#1038
1#
b10000110 &
#1039
0#
#1040
1#
b10000111 &
#1041
0#
#1042
1#
b10001000 &
#1043
0#
#1044
1#
b10001001 &
#1045
0#
#1046
1#
b10001010 &
#1047
0#
#1048
1#
b10001011 &
#1049
0#
#1050
1#
b10001100 &
#1051
0#
#1052
1#
b10001101 &
#1053
0#
#1054
1#
b10001110 &
#1055
0#
#1056
1#
b10001111 &
#1057
0#
#1058
1#
b10010000 &
#1059
0#
#1060
1#
b10010001 &
#1061
0#
#1062
1#
b10010010 &
#1063
0#
#1064
1#
b10010011 &
#1065
0#
#1066
1#
b10010100 &
#1067
0#
#1068
1#
b10010101 &
#1069
0#
#1070
1#
b10010110 &
#1071
0#
#1072
1#
b10010111 &
#1073
0#
#1074
1#
b10011000 &
#1075
0#
#1076
1#
b10011001 &
#1077
0#
#1078
1#
b10011010 &
#1079
0#
#1080
1#
b10011011 &
#1081
0#
#1082
1#
b10011100 &
#1083
0#
#1084
1#
b10011101 &
#1085
0#
#1086
1#
b10011110 &
#1087
0#
#1088
1#
b10011111 &
#1089
0#
#1090
1#
b10100000 &
#1091
0#
#1092
1#
0%
b10100001 &
#1093
0#
#1094
1#
b10100000 &
#1095
0#
#1096
1#
b10011111 &
#1097
0#
#1098
1#
b10011110 &
#1099
0#
#1100
1#
b10011101 &
#1101
0#
#1102
1#
b10011100 &
#1103
0#
#1104
1#
b10011011 &
#1105
0#
#1106
1#
b10011010 &
#1107
0#
#1108
1#
b10011001 &
#1109
0#
#1110
1#
b10011000 &
#1111
0#
#1112
1#
b10010111 &
#1113
0#
#1114
1#
b10010110 &
#1115
0#
#1116
1#
b10010101 &
#1117
0#
#1118
1#
b10010100 &
#1119
0#
#1120
1#
b10010011 &
#1121
0#
#1122
1#
b10010010 &
#1123
0#
#1124
1#
b10010001 &
#1125
0#
#1126
1#
b10010000 &
#1127
0#
#1128
1#
b10001111 &
#1129
0#
#1130
1#
b10001110 &
#1131
0#
#1132
1#
b10001101 &
#1133
0#
#1134
1#
b10001100 &
#1135
0#
#1136
1#
b10001011 &
#1137
0#
#1138
1#
b10001010 &
#1139
0#
#1140
1#
b10001001 &
#1141
0#
#1142
1#
b10001000 &
#1143
0#
#1144
1#
b10000111 &
#1145
0#
#1146
1#
b10000110 &
#1147
0#
#1148
1#
b10000101 &
#1149
0#
#1150
1#
b10000100 &
#1151
0#
#1152
1#
b10000011 &
#1153
0#
#1154
1#
b10000010 &
#1155
0#
#1156
1#
b10000001 &
#1157
0#
#1158
1#
b10000000 &
#1159
0#
#1160
1#
b01111111 &
#1161
0#
#1162
1#
b01111110 &
#1163
0#
#1164
1#
b01111101 &
#1165
0#
#1166
1#
b01111100 &
#1167
0#
#1168
1#
b01111011 &
#1169
0#
#1170
1#
b01111010 &
#1171
0#
#1172
1#
b01111001 &
#1173
0#
#1174
1#
b01111000 &
#1175
0#
#1176
1#
b01110111 &
#1177
0#
#1178
1#
b01110110 &
#1179
0#
#1180
1#
b01110101 &
#1181
0#
#1182
1#
b01110100 &
#1183
0#
#1184
1#
b01110011 &
#1185
0#
#1186
1#
b01110010 &
#1187
0#
#1188
1#
b01110001 &
#1189
0#
#1190
1#
b01110000 &
#1191
0#
#1192
1#
b01101111 &
#1193
0#
#1194
1#
b01101110 &
#1195
0#
#1196
1#
b01101101 &
#1197
0#
#1198
1#
b01101100 &
#1199
0#
#1200
1#
b01101011 &
#1201
0#
#1202
1#
b01101010 &
#1203
0#
#1204
1#
b01101001 &
#1205
0#
#1206
1#
b01101000 &
#1207
0#
#1208
1#
b01100111 &
#1209
0#
#1210
1#
b01100110 &
#1211
0#
#1212
1#
b01100101 &
#1213
0#
#1214
1#
b01100100 &
#1215
0#
#1216
1#
b01100011 &
#1217
0#
#1218
1#
b01100010 &
#1219
0#
#1220
1#
b01100001 &
#1221
0#
#1222
1#
b01100000 &
#1223
0#
#1224
1#
b01011111 &
#1225
0#
#1226
1#
b01011110 &
#1227
0#
#1228
1#
b01011101 &
#1229
0#
#1230
1#
b01011100 &
#1231
0#
#1232
1#
b01011011 &
#1233
0#
#1234
1#
b01011010 &
#1235
0#
#1236
1#
b01011001 &
#1237
0#
#1238
1#
b01011000 &
#1239
0#
#1240
1#
b01010111 &
#1241
0#
#1242
1#
b01010110 &
#1243
0#
#1244
1#
b01010101 &
#1245
0#
#1246
1#
b01010100 &
#1247
0#
#1248
1#
b01010011 &
#1249
0#
#1250
1#
b01010010 &
#1251
0#
#1252
1#
b01010001 &
#1253
0#
#1254
1#
b01010000 &
#1255
0#
#1256
1#
b01001111 &
#1257
0#
#1258
1#
b01001110 &
#1259
0#
#1260
1#
b01001101 &
#1261
0#
#1262
1#
b01001100 &
#1263
0#
#1264
1#
b01001011 &
#1265
0#
#1266
1#
b01001010 &
#1267
0#
#1268
1#
b01001001 &
#1269
0#
#1270
1#
b01001000 &
#1271
0#
#1272
1#
b01000111 &
#1273
0#
#1274
1#
b01000110 &
#1275
0#
#1276
1#
b01000101 &
#1277
0#
#1278
1#
b01000100 &
#1279
0#
#1280
1#
b01000011 &
#1281
0#
#1282
1#
b01000010 &
#1283
0#
#1284
1#
b01000001 &
#1285
0#
#1286
1#
b01000000 &
#1287
0#
#1288
1#
b00111111 &
#1289
0#
#1290
1#
1%
b00111110 &
#1291
0#
#1292
1#
b00111111 &
#1293
0#
#1294
1#
b01000000 &
#1295
0#
#1296
1#
b01000001 &
#1297
0#
#1298
1#
b01000010 &
#1299
0#
#1300
1#
b01000011 &
#1301
0#
#1302
1#
b01000100 &
#1303
0#
#1304
1#
b01000101 &
#1305
0#
#1306
1#
b01000110 &
#1307
0#
#1308
1#
b01000111 &
#1309
0#
#1310
1#
b01001000 &
#1311
0#
#1312
1#
b01001001 &
#1313
0#
#1314
1#
b01001010 &
#1315
0#
#1316
1#
b01001011 &
#1317
0#
#1318
1#
b01001100 &
#1319
0#
#1320
1#
b01001101 &
#1321
0#
#1322
1#
b01001110 &
#1323
0#
#1324
1#
b01001111 &
#1325
0#
#1326
1#
b01010000 &
#1327
0#
#1328
1#
b01010001 &
#1329
0#
#1330
1#
b01010010 &
#1331
0#
#1332
1#
b01010011 &
#1333
0#
#1334
1#
b01010100 &
#1335
0#
#1336
1#
b01010101 &
#1337
0#
#1338
1#
b01010110 &
#1339
0#
#1340
1#
b01010111 &
#1341
0#
#1342
1#
b01011000 &
#1343
0#
#1344
1#
b01011001 &
#1345
0#
#1346
1#
b01011010 &
#1347
0#
#1348
1#
b01011011 &
#1349
0#
#1350
1#
b01011100 &
#1351
0#
#1352
1#
b01011101 &
#1353
0#
#1354
1#
b01011110 &
#1355
0#
#1356
1#
b01011111 &
#1357
0#
#1358
1#
b01100000 &
#1359
0#
#1360
1#
b01100001 &
#1361
0#
#1362
1#
b01100010 &
#1363
0#
#1364
1#
b01100011 &
#1365
0#
#1366
1#
b01100100 &
#1367
0#
#1368
1#
b01100101 &
#1369
0#
#1370
1#
b01100110 &
#1371
0#
#1372
1#
b01100111 &
#1373
0#
#1374
1#
b01101000 &
#1375
0#
#1376
1#
b01101001 &
#1377
0#
#1378
1#
b01101010 &
#1379
0#
#1380
1#
b01101011 &
#1381
0#
#1382
1#
b01101100 &
#1383
0#
#1384
1#
b01101101 &
#1385
0#
#1386
1#
b01101110 &
#1387
0#
#1388
1#
b01101111 &
#1389
0#
#1390
1#
b01110000 &
#1391
0#
#1392
1#
b01110001 &
#1393
0#
#1394
1#
b01110010 &
#1395
0#
#1396
1#
b01110011 &
#1397
0#
#1398
1#
b01110100 &
#1399
0#
#1400
1#
b01110101 &
#1401
0#
#1402
1#
b01110110 &
#1403
0#
#1404
1#
b01110111 &
#1405
0#
#1406
1#
b01111000 &
#1407
0#
#1408
1#
b01111001 &
#1409
0#
#1410
1#
b01111010 &
#1411
0#
#1412
1#
b01111011 &
#1413
0#
#1414
1#
b01111100 &
#1415
0#
#1416
1#
b01111101 &
#1417
0#
#1418
1#
b01111110 &
#1419
0#
#1420
1#
b01111111 &
#1421
0#
#1422
1#
b10000000 &
#1423
0#
#1424
1#
b10000001 &
#1425
0#
#1426
1#
b10000010 &
#1427
0#
#1428
1#
b10000011 &
#1429
0#
#1430
1#
b10000100 &
#1431
0#
#1432
1#
b10000101 &
#1433
0#
#1434
1#
b10000110 &
#1435
0#
#1436
1#
b10000111 &
#1437
0#
#1438
1#
b10001000 &
#1439
0#
#1440
1#
b10001001 &
#1441
0#
#1442
1#
b10001010 &
#1443
0#
#1444
1#
b10001011 &
#1445
0#
#1446
1#
b10001100 &
#1447
0#
#1448
1#
b10001101 &
#1449
0#
#1450
1#
b10001110 &
#1451
0#
#1452
1#
b10001111 &
#1453
0#
#1454
1#
b10010000 &
#1455
0#
#1456
1#
b10010001 &
#1457
0#
#1458
1#
b10010010 &
#1459
0#
#1460
1#
b10010011 &
#1461
0#
#1462
1#
b10010100 &
#1463
0#
#1464
1#
b10010101 &
#1465
0#
#1466
1#
b10010110 &
#1467
0#
#1468
1#
b10010111 &
#1469
0#
#1470
1#
b10011000 &
#1471
0#
